templated_email/__init__.py
templated_email/models.py
templated_email/tests.py
templated_email/utils.py
templated_email/backends/__init__.py
templated_email/backends/mailchimp_sts.py
templated_email/backends/postageapp_backend.py
templated_email/backends/vanilla_django.py
django_templated_email_pebble-2.1.0.dist-info/AUTHORS
django_templated_email_pebble-2.1.0.dist-info/LICENSE
django_templated_email_pebble-2.1.0.dist-info/METADATA
django_templated_email_pebble-2.1.0.dist-info/WHEEL
django_templated_email_pebble-2.1.0.dist-info/top_level.txt
django_templated_email_pebble-2.1.0.dist-info/RECORD
