Metadata-Version: 2.1
Name: django-templated-email-pebble
Version: 2.1.0
Summary: Pebble's fork of a Django oriented templated / transaction email abstraction
Home-page: http://github.com/mypebble/django-templated-email/
Author: SF Software limited t/a Pebble
Author-email: sysadmin@talktopebble.co.uk
License: MIT
Platform: any
Classifier: Development Status :: 5 - Production/Stable
Classifier: Intended Audience :: Developers
Classifier: License :: OSI Approved :: MIT License
Classifier: Operating System :: OS Independent
Classifier: Programming Language :: Python
Classifier: Programming Language :: Python :: 3.8
Classifier: Programming Language :: Python :: 3.9
Classifier: Programming Language :: Python :: 3.10
Classifier: Programming Language :: Python :: 3.11
Classifier: Programming Language :: Python :: 3.12
Classifier: Topic :: Software Development :: Libraries :: Python Modules
Classifier: Framework :: Django
Classifier: Framework :: Django :: 4.0
Classifier: Framework :: Django :: 4.1
Classifier: Framework :: Django :: 4.2
License-File: LICENSE
License-File: AUTHORS
Requires-Dist: six
